{"v1_0": {"current": 100, "total": 100, "status": "completed", "error": null, "time": "20:35:26"}, "v1_2": {"current": 100, "total": 100, "status": "completed", "error": null, "time": "20:35:46"}, "sector_v2_full_1728": {"current": 500, "total": 500, "status": "completed", "error": null, "time": "17:45:26"}, "sector_v2_eod_2320": {"current": 500, "total": 500, "status": "completed", "error": null, "time": "23:21:13"}, "v2_0": {"current": 100, "total": 100, "status": "completed", "error": null, "time": "13:45:50", "logs": ["[13:45:50] \ud83d\udd0d Analyzed 100/505 stocks\u2026", "[13:45:50] \ud83d\udd0d Analyzed 150/505 stocks\u2026", "[13:45:50] \ud83d\udd0d Analyzed 200/505 stocks\u2026", "[13:45:50] \ud83d\udd0d Analyzed 250/505 stocks\u2026", "[13:45:50] \ud83d\udd0d Analyzed 300/505 stocks\u2026", "[13:45:50] \ud83d\udd0d Analyzed 350/505 stocks\u2026", "[13:45:50] \ud83d\udd0d Analyzed 400/505 stocks\u2026", "[13:45:50] \ud83d\udd0d Analyzed 450/505 stocks\u2026", "[13:45:50] \ud83d\udd0d Analyzed 500/505 stocks\u2026", "[13:45:50] \u2705 Done! Report saved \u2192 momentum_report_v2_10k.html"]}, "v2_1": {"current": 100, "total": 100, "status": "completed", "error": null, "time": "07:35:16", "logs": ["[07:35:12] \u23ec Batch 10/11 done \u2014 \u2713299 fetched so far", "[07:35:16] \u23ec Batch 11/11 done \u2014 \u2713314 fetched so far", "[07:35:16] yfinance done: \u2713314 \u27170 / 315", "[07:35:16] \u2705 Data ready (314 symbols) \u2014 calculating momentum scores", "[07:35:16] \ud83d\udd0d Analyzed 50/315 stocks\u2026", "[07:35:16] \ud83d\udd0d Analyzed 100/315 stocks\u2026", "[07:35:16] \ud83d\udd0d Analyzed 150/315 stocks\u2026", "[07:35:16] \ud83d\udd0d Analyzed 200/315 stocks\u2026", "[07:35:16] \ud83d\udd0d Analyzed 250/315 stocks\u2026", "[07:35:16] \ud83d\udd0d Analyzed 300/315 stocks\u2026"]}, "sector_v2_eod_0751": {"current": 0, "total": 511, "status": "error", "error": "Process interrupted (stale)", "time": "07:51:13"}, "sector_v2_eod_1346": {"current": 500, "total": 500, "status": "completed", "error": null, "time": "14:09:23"}, "v3_1": {"current": 100, "total": 100, "status": "completed", "error": null, "time": "14:34:11", "logs": ["[14:22:35] \u23ec Batch 11/11 done \u2014 \u2713236 fetched so far", "[14:22:35] yfinance done: \u2713236 \u27170 / 315", "[14:22:35] \u2705 Data ready (236 symbols) \u2014 running V3 deep analysis", "[14:23:52] \ud83d\udd0d Analyzed 50/315 stocks\u2026", "[14:25:01] \ud83d\udd0d Analyzed 100/315 stocks\u2026", "[14:25:53] \ud83d\udd0d Analyzed 150/315 stocks\u2026", "[14:26:42] \ud83d\udd0d Analyzed 200/315 stocks\u2026", "[14:27:40] \ud83d\udd0d Analyzed 250/315 stocks\u2026", "[14:33:23] \ud83d\udd0d Analyzed 300/315 stocks\u2026", "[14:34:11] \u2705 Done! Report saved \u2192 momentum_report_v3_20k.html"]}}